json2csv/__init__.py
json2csv/json2csv.py
json2csv-1.0.1.dist-info/METADATA
json2csv-1.0.1.dist-info/WHEEL
json2csv-1.0.1.dist-info/top_level.txt
json2csv-1.0.1.dist-info/RECORD
