Metadata-Version: 2.1
Name: json2csv
Version: 1.0.1
Summary: Library for converting JSON to CSV
Home-page: UNKNOWN
Author: Ed
Author-email: agabsed@gmail.com
License: UNKNOWN
Platform: UNKNOWN
